omnimrz
venv
