Metadata-Version: 2.4
Name: omnimrz
Version: 0.1.1
Summary: Fast and robust MRZ extraction, parsing, and validation using PaddleOCR
Author-email: Azwad Fawad Hasan <azwadfawadhasan@gmail.com>
License: Apache-2.0
Project-URL: Homepage, https://github.com/AzwadFawadHasan/OmniMRZ
Project-URL: Issues, https://github.com/AzwadFawadHasan/OmniMRZ/issues
Keywords: mrz,passport,ocr,identity,paddleocr
Requires-Python: >=3.8
License-File: LICENSE
Requires-Dist: paddleocr
Requires-Dist: paddlepaddle
Dynamic: license-file
